thoth/messaging/__init__.py
thoth/messaging/admin_client.py
thoth/messaging/advise_justification.py
thoth/messaging/adviser_trigger.py
thoth/messaging/build_analysis_trigger.py
thoth/messaging/config.py
thoth/messaging/consumer.py
thoth/messaging/cve_provided.py
thoth/messaging/hash_mismatch.py
thoth/messaging/inspection_complete.py
thoth/messaging/kebechet_run_url.py
thoth/messaging/kebechet_trigger.py
thoth/messaging/message_base.py
thoth/messaging/message_factory.py
thoth/messaging/missing_package.py
thoth/messaging/missing_version.py
thoth/messaging/package_extract_trigger.py
thoth/messaging/package_releases.py
thoth/messaging/producer.py
thoth/messaging/provenance_checker_trigger.py
thoth/messaging/py.typed
thoth/messaging/si_unanalyzed_package.py
thoth/messaging/solved_package.py
thoth/messaging/thoth_repo_init.py
thoth/messaging/unresolved_package.py
thoth/messaging/unrevsolved_package.py
thoth/messaging/update_provides_src_distro.py
thoth_messaging-0.16.2.dist-info/LICENSE
thoth_messaging-0.16.2.dist-info/METADATA
thoth_messaging-0.16.2.dist-info/WHEEL
thoth_messaging-0.16.2.dist-info/top_level.txt
thoth_messaging-0.16.2.dist-info/RECORD
