Metadata-Version: 2.1
Name: thoth-messaging
Version: 0.16.2
Summary: Messaging module of Project Thoth
Author: Christoph Görn
Author-email: goern@redhat.com
License: GPLv3+
License-File: LICENSE
Requires-Dist: confluent-kafka
Requires-Dist: thoth-common
Requires-Dist: click
Requires-Dist: pydantic
